arcane/workflows.py
arcane_workflows-0.2.4.dist-info/METADATA
arcane_workflows-0.2.4.dist-info/WHEEL
arcane_workflows-0.2.4.dist-info/RECORD
