Metadata-Version: 2.3
Name: arcane-workflows
Version: 0.2.4
Summary: Package description
Author: Arcane
Author-email: product@wearcane.com
Requires-Python: >=3.8,<4.0
Classifier: Programming Language :: Python :: 3
Classifier: Programming Language :: Python :: 3.8
Classifier: Programming Language :: Python :: 3.9
Classifier: Programming Language :: Python :: 3.10
Classifier: Programming Language :: Python :: 3.11
Classifier: Programming Language :: Python :: 3.12
Classifier: Programming Language :: Python :: 3.13
Requires-Dist: backoff (>=1.10.0)
Requires-Dist: google-cloud-workflows (==1.8.0)
Requires-Dist: urllib3 (>=2.2.3,<3.0.0)
